{
  "context-menu": {
    "atom-text-editor": [
      {
        "label": "Take screenshot and save to relative destination",
        "command": "kali-markdown-insert-screenshot:screenshot-to-relative-destination"
      }
    ]
  },
  "menu": [
    {
      "label": "Packages",
      "submenu": [
        {
          "label": "kali-markdown-insert-screenshot",
          "submenu": [
            {
              "label": "Take screenshot and save to relative destination",
              "command": "kali-markdown-insert-screenshot:screenshot-to-relative-destination"
            }
          ]
        }
      ]
    }
  ]
}
